he_scheduling/__init__.py
he_scheduling/api/__init__.py
he_scheduling/api/v1/__init__.py
he_scheduling/api/v1/master_planning.py
he_scheduling/api/v2/__init__.py
he_scheduling/api/v2/master_planning.py
he_scheduling/core/__init__.py
he_scheduling/core/celery.py
he_scheduling/core/config.py
he_scheduling/core/logging.py
he_scheduling/core/version.py
he_scheduling/main.py
he_scheduling/models/__init__.py
he_scheduling/models/master_planning.py
he_scheduling/services/__init__.py
he_scheduling/services/master_planning.py
he_scheduling/tasks/__init__.py
he_scheduling/tasks/master_planning.py
he_scheduling-0.5.0.dist-info/LICENSE
he_scheduling-0.5.0.dist-info/METADATA
he_scheduling-0.5.0.dist-info/WHEEL
he_scheduling-0.5.0.dist-info/entry_points.txt
he_scheduling-0.5.0.dist-info/RECORD
